[{"name":"Mahabubul","email":"mahabubul470@gmail.com","username":"Hasan","password":"22222222@","gender":"male","dob":"1-1-2002"},{"name":"Mahabubul","email":"mahabubul470@gmail.com","username":"Hasan","password":"22222222@","gender":"male","dob":"1-1-2002"},{"name":"Mahabubul","email":"mahabubul470@gmail.com","username":"Hasan","password":"22222222@","gender":"male","dob":"1-1-2002"},{"name":"Mahabubul","email":"mahabubul470@gmail.com","username":"Hasan","password":"22222222@","gender":"male","dob":"1-1-2002"},{"name":"Mahabubul","email":"mahabubul470@gmail.com","username":"Hasan","password":"22222222@","gender":"male","dob":"1-1-2002"},{"name":"Mahabubul","email":"mahabubul470@gmail.com","username":"Hasan","password":"22222222@","gender":"male","dob":"1-1-2002"}]